AUTHORS
CHANGELOG
COPYING
MANIFEST.in
README.md
setup.py
mapturner/__init__.py
mapturner.egg-info/PKG-INFO
mapturner.egg-info/SOURCES.txt
mapturner.egg-info/dependency_links.txt
mapturner.egg-info/entry_points.txt
mapturner.egg-info/requires.txt
mapturner.egg-info/top_level.txt